.gitattributes
.gitignore
.gitmodules
.local.jenkins.win.yml
.travis.yml
LICENSE.txt
README.rst
appveyor.yml
build_script.bat
requirements.txt
setup.py
.circleci/config.yml
C:/xavierdupre/__home_/GitHub/csharpyml/src/csharpyml/cparts/cmodule.cpp
C:/xavierdupre/__home_/GitHub/csharpyml/src/csharpyml/cparts/version.cpp
_doc/examples/README.txt
_doc/notebooks/csharp_for_ml_in_notebook.ipynb
_doc/sphinxdoc/source/conf.py
_doc/sphinxdoc/source/glossary.rst
_doc/sphinxdoc/source/i_ex.rst
_doc/sphinxdoc/source/i_faq.rst
_doc/sphinxdoc/source/i_nb.rst
_doc/sphinxdoc/source/index.rst
_doc/sphinxdoc/source/indexmenu.rst
_doc/sphinxdoc/source/license.rst
_doc/sphinxdoc/source/api/index.rst
_doc/sphinxdoc/source/blog/2018/2018-05-21_firstblog.rst
_doc/sphinxdoc/source/phdoc_static/project_ico.ico
_doc/sphinxdoc/source/phdoc_static/project_ico.png
_unittests/run_unittests.py
_unittests/ut_binaries/test_maml.py
_unittests/ut_binaries/test_maml0.py
_unittests/ut_binaries/test_maml_nb.py
_unittests/ut_cparts/test_cmodule.py
_unittests/ut_documentation/test_run_notebooks.py
_unittests/ut_module/test_code_style.py
_unittests/ut_module/test_convert_notebooks.py
_unittests/ut_module/test_csharp_version.py
_unittests/ut_module/test_readme.py
_unittests/ut_module/test_version.py
cscode/CSharPyMLExtension_netcore.sln
cscode/CSharPyMLExtension/CSharPyMLExtension.csproj
cscode/CSharPyMLExtension/Constants.cs
cscode/CSharPyMLExtension/MamlHelper.cs
csharpyml.egg-info/PKG-INFO
csharpyml.egg-info/SOURCES.txt
csharpyml.egg-info/dependency_links.txt
csharpyml.egg-info/requires.txt
csharpyml.egg-info/top_level.txt
src/__init__.py
src/csharpyml/__init__.py
src/csharpyml/binaries/__init__.py
src/csharpyml/binaries/add_reference.py
src/csharpyml/binaries/maml_helper.py
src/csharpyml/cparts/__init__.py
src/csharpyml/cparts/cmodule.cpp
src/csharpyml/cparts/version.cpp
src/csharpyml/cparts/version.hpp
src/csharpyml/notebook/__init__.py
src/csharpyml/notebook/csmlmagics.py